along-0.0.0.dist-info/METADATA
along-0.0.0.dist-info/WHEEL
along/__init__.py
along-0.0.0.dist-info/RECORD
