Metadata-Version: 2.1
Name: along
Version: 0.0.0
Summary: Along: Code Flow Demonstrator for Beginners
Author-Email: zetaloop <zetaloop@outlook.com>
License: MIT
Requires-Python: >=3.7
